odoo/addons/crm_metadata/__init__.py
odoo/addons/crm_metadata/__manifest__.py
odoo/addons/crm_metadata/models/__init__.py
odoo/addons/crm_metadata/models/crm_lead.py
odoo/addons/crm_metadata/models/crm_lead_metadata_line.py
odoo/addons/crm_metadata/security/ir.model.access.csv
odoo/addons/crm_metadata/views/crm_lead.xml
odoo_addon_crm_metadata-16.0.0.1.1.dist-info/METADATA
odoo_addon_crm_metadata-16.0.0.1.1.dist-info/WHEEL
odoo_addon_crm_metadata-16.0.0.1.1.dist-info/top_level.txt
odoo_addon_crm_metadata-16.0.0.1.1.dist-info/RECORD
